coolipy/__init__.py
coolipy/constants.py
coolipy/exceptions.py
coolipy/models/applications.py
coolipy/models/base.py
coolipy/models/coolify_api_response.py
coolipy/models/databases.py
coolipy/models/deployments.py
coolipy/models/env_vars.py
coolipy/models/environs.py
coolipy/models/private_keys.py
coolipy/models/projects.py
coolipy/models/resources.py
coolipy/models/servers.py
coolipy/models/service.py
coolipy/models/teams.py
coolipy/services/http_service.py
coolipy/services/coolify_api/applications.py
coolipy/services/coolify_api/base.py
coolipy/services/coolify_api/databases.py
coolipy/services/coolify_api/deployments.py
coolipy/services/coolify_api/private_keys.py
coolipy/services/coolify_api/projects.py
coolipy/services/coolify_api/resources.py
coolipy/services/coolify_api/servers.py
coolipy/services/coolify_api/services.py
coolipy/services/coolify_api/teams.py
coolipy-0.0.8.dist-info/LICENSE
coolipy-0.0.8.dist-info/METADATA
coolipy-0.0.8.dist-info/WHEEL
coolipy-0.0.8.dist-info/top_level.txt
coolipy-0.0.8.dist-info/RECORD
