Metadata-Version: 2.2
Name: coolipy
Version: 0.0.8
Summary: Coolipy - (Un)official Coolify - coolify.io - Python client!
Author-email: Gabriel Bocchini <gabrielbocchini@gmail.com>
Maintainer-email: Gabriel Bocchini <gabrielbocchini@gmail.com>
Project-URL: Homepage, https://github.com/gbbocchini/coolipy
Project-URL: Documentation, https://coolipydocs.gabrielbocchini.com.br/
Project-URL: Repository, https://github.com/gbbocchini/coolipy
Keywords: coolify,rest client,api client
Classifier: Development Status :: 5 - Production/Stable
Classifier: Intended Audience :: Developers
Classifier: Intended Audience :: Education
Classifier: Programming Language :: Python :: 3
Classifier: License :: OSI Approved :: Apache Software License
Classifier: Operating System :: OS Independent
Requires-Python: >=3.10
License-File: LICENSE
Requires-Dist: requests>=2.32.3
